chap/backends/replay.py
chap_backend_replay-0.0.3.dist-info/METADATA
chap_backend_replay-0.0.3.dist-info/WHEEL
chap_backend_replay-0.0.3.dist-info/top_level.txt
chap_backend_replay-0.0.3.dist-info/RECORD
