Metadata-Version: 2.1
Name: chap-backend-replay
Version: 0.0.3
Summary: Session-replaying backend for chap
Author-email: Jeff Epler <jepler@gmail.com>
Project-URL: homepage, https://github.com/jepler/chap-backend-replay
Project-URL: repository, https://github.com/jepler/chap-backend-replay
Classifier: Programming Language :: Python :: 3
Classifier: Programming Language :: Python :: 3.10
Classifier: Programming Language :: Python :: 3.11
Classifier: Programming Language :: Python :: 3.12
Classifier: Programming Language :: Python :: Implementation :: PyPy
Classifier: Programming Language :: Python :: Implementation :: CPython
Classifier: License :: OSI Approved :: MIT License
Classifier: Operating System :: OS Independent
Requires-Dist: chap
